flask_rip.py
flask_restinpeace-1.4.0.dist-info/LICENSE
flask_restinpeace-1.4.0.dist-info/METADATA
flask_restinpeace-1.4.0.dist-info/WHEEL
flask_restinpeace-1.4.0.dist-info/top_level.txt
flask_restinpeace-1.4.0.dist-info/RECORD
