Metadata-Version: 2.1
Name: flask-restinpeace
Version: 1.4.0
Summary: Create Flask REST APIs in peace.
Home-page: https://github.com/kynikos/lib.py.flask-rip
Author: Dario Giovannetti
Author-email: dev@dariogiovannetti.net
License: MIT
Keywords: flask rest restful api marshal marshmallow
Platform: UNKNOWN
Classifier: Development Status :: 4 - Beta
Classifier: Environment :: Web Environment
Classifier: Framework :: Flask
Classifier: Intended Audience :: Developers
Classifier: License :: OSI Approved :: MIT License
Classifier: Programming Language :: Python :: 2
Classifier: Programming Language :: Python :: 2.6
Classifier: Programming Language :: Python :: 2.7
Classifier: Programming Language :: Python :: 3
Classifier: Programming Language :: Python :: 3.6
Classifier: Programming Language :: Python :: 3.7
Classifier: Topic :: Internet :: WWW/HTTP :: WSGI :: Middleware
